numcodecs_wasm_linear_quantize/__init__.py
numcodecs_wasm_linear_quantize/__init__.pyi
numcodecs_wasm_linear_quantize/codec.wasm
numcodecs_wasm_linear_quantize/py.typed
numcodecs_wasm_linear_quantize-0.5.0.dist-info/METADATA
numcodecs_wasm_linear_quantize-0.5.0.dist-info/WHEEL
numcodecs_wasm_linear_quantize-0.5.0.dist-info/entry_points.txt
numcodecs_wasm_linear_quantize-0.5.0.dist-info/top_level.txt
numcodecs_wasm_linear_quantize-0.5.0.dist-info/RECORD
